MANIFEST.in
README.rst
setup.py
docs/HISTORY.txt
docs/INSTALL.txt
docs/LICENSE.GPL
docs/LICENSE.txt
docs/TODO.txt
unice/.DS_Store
unice/__init__.py
unice.portlet.profil.egg-info/PKG-INFO
unice.portlet.profil.egg-info/SOURCES.txt
unice.portlet.profil.egg-info/dependency_links.txt
unice.portlet.profil.egg-info/entry_points.txt
unice.portlet.profil.egg-info/namespace_packages.txt
unice.portlet.profil.egg-info/not-zip-safe
unice.portlet.profil.egg-info/requires.txt
unice.portlet.profil.egg-info/top_level.txt
unice/portlet/.DS_Store
unice/portlet/__init__.py
unice/portlet/profil/.DS_Store
unice/portlet/profil/__init__.py
unice/portlet/profil/configure.zcml
unice/portlet/profil/profilportlet.pt
unice/portlet/profil/profilportlet.py
unice/portlet/profil/vocabularies.py
unice/portlet/profil/browser/.DS_Store
unice/portlet/profil/browser/__init__.py
unice/portlet/profil/browser/configure.zcml
unice/portlet/profil/browser/stylesheets/styles.css
unice/portlet/profil/profiles/.DS_Store
unice/portlet/profil/profiles/default/cssregistry.xml
unice/portlet/profil/profiles/default/metadata.xml
unice/portlet/profil/profiles/default/portlets.xml
unice/portlet/profil/tests/__init__.py
unice/portlet/profil/tests/base.py
unice/portlet/profil/tests/test_portlet.py